README.md
setup.cfg
setup.py
postgresqlconnector/__init__.py
postgresqlconnector/connector.py
postgresqlconnector/transaction.py
postgresqlconnector.egg-info/PKG-INFO
postgresqlconnector.egg-info/SOURCES.txt
postgresqlconnector.egg-info/dependency_links.txt
postgresqlconnector.egg-info/requires.txt
postgresqlconnector.egg-info/top_level.txt