Metadata-Version: 2.1
Name: postgresqlconnector
Version: 0.6
Summary: A small module for working quickly with the PostgreSQL
Home-page: https://github.com/sidan93/postgresql_connector
Author: Sidorov A.B.
Author-email: sidan93@gmail.com
License: MIT
Download-URL: https://github.com/sidan93/postgresql_connector/archive/v0.6.tar.gz
Keywords: Postgre,PostgreSQL,connector,postgresqlconnection,postgresql connector
Platform: UNKNOWN
Classifier: Development Status :: 4 - Beta
Classifier: Intended Audience :: Developers
Classifier: Topic :: Software Development :: Build Tools
Classifier: License :: OSI Approved :: MIT License
Classifier: Programming Language :: Python :: 3
Classifier: Programming Language :: Python :: 3.4
Classifier: Programming Language :: Python :: 3.5
Classifier: Programming Language :: Python :: 3.6
Classifier: Programming Language :: Python :: 3.7
